quez/__init__.py
quez/base.py
quez/compressors.py
quez/deques.py
quez/queues.py
quez-1.1.1.dist-info/LICENSE
quez-1.1.1.dist-info/METADATA
quez-1.1.1.dist-info/WHEEL
quez-1.1.1.dist-info/RECORD
