Metadata-Version: 2.3
Name: quez
Version: 1.1.1
Summary: Pluggable, compressed in-memory queues for both sync and asyncio applications.
License: MIT
Author: Chaiwat Suttipongsakul
Author-email: cwt@bashell.com
Requires-Python: >=3.10,<4.0
Classifier: License :: OSI Approved :: MIT License
Classifier: Programming Language :: Python :: 3
Classifier: Programming Language :: Python :: 3.10
Classifier: Programming Language :: Python :: 3.11
Classifier: Programming Language :: Python :: 3.12
Classifier: Programming Language :: Python :: 3.13
Provides-Extra: all
Provides-Extra: lzo
Provides-Extra: zstd
Requires-Dist: python-lzo ; extra == "all"
Requires-Dist: python-lzo ; extra == "lzo"
Requires-Dist: zstandard ; extra == "all"
Requires-Dist: zstandard ; extra == "zstd"
Project-URL: GitHub Mirror, https://github.com/cwt/quez
Project-URL: Homepage, https://sr.ht/~cwt/quez/
Project-URL: Repository, https://hg.sr.ht/~cwt/quez
